cranetoolbox/__init__.py
cranetoolbox/fileHandler.py
cranetoolbox/analysis/__init__.py
cranetoolbox/analysis/__main__.py
cranetoolbox/analysis/countOccurences.py
cranetoolbox/importTools/__init__.py
cranetoolbox/importTools/__main__.py
cranetoolbox/importTools/transform.py
cranetoolbox/preprocess/__init__.py
cranetoolbox/preprocess/__main__.py
cranetoolbox/preprocess/preprocess.py
cranetoolbox/preprocess/preprocessTools.py
cranetoolbox-0.1.1.dist-info/LICENSE
cranetoolbox-0.1.1.dist-info/METADATA
cranetoolbox-0.1.1.dist-info/WHEEL
cranetoolbox-0.1.1.dist-info/entry_points.txt
cranetoolbox-0.1.1.dist-info/top_level.txt
cranetoolbox-0.1.1.dist-info/RECORD
