Metadata-Version: 2.1
Name: cranetoolbox
Version: 0.1.1
Summary: A package against racism around COVID-19
Home-page: https://github.com/CRANE-toolbox/analysis-pipelines
Author: The CRANE Team
Author-email: author@example.com
License: UNKNOWN
Platform: UNKNOWN
Classifier: Development Status :: 2 - Pre-Alpha
Classifier: License :: OSI Approved :: GNU Affero General Public License v3
Classifier: Operating System :: OS Independent
Requires-Python: >=3.6
Requires-Dist: argparse
Requires-Dist: datetime
Requires-Dist: num2words
Requires-Dist: pathlib
Requires-Dist: pandas
Requires-Dist: typing
Requires-Dist: wordsegment
